<?xml version="1.0" encoding="UTF-8" ?><TAData><time>2020-05-19 18:17:27.946708</time><SC_T1>27.18</SC_T1><CC_T1>24.91</CC_T1><DPG_T1>22.25</DPG_T1><pCO2>779.025</pCO2><pH2O>13.6765</pH2O><Sample_weight>0.4736328125</Sample_weight></TAData>
<?xml version="1.0" encoding="UTF-8" ?><TAData><time>2020-05-19 18:17:29.949884</time><SC_T1>27.18</SC_T1><CC_T1>24.99</CC_T1><DPG_T1>22.25</DPG_T1><pCO2>779.975</pCO2><pH2O>13.6657</pH2O><Sample_weight>0.47607421875</Sample_weight></TAData>
<?xml version="1.0" encoding="UTF-8" ?><TAData><time>2020-05-19 18:17:31.953225</time><SC_T1>27.18</SC_T1><CC_T1>25.12</CC_T1><DPG_T1>22.25</DPG_T1><pCO2>785.194</pCO2><pH2O>13.6595</pH2O><Sample_weight>0.46630859375</Sample_weight></TAData>
<?xml version="1.0" encoding="UTF-8" ?><TAData><time>2020-05-19 18:17:33.955872</time><SC_T1>27.18</SC_T1><CC_T1>25.3</CC_T1><DPG_T1>22.26</DPG_T1><pCO2>792.317</pCO2><pH2O>13.6522</pH2O><Sample_weight>0.47607421875</Sample_weight></TAData>
<?xml version="1.0" encoding="UTF-8" ?><TAData><time>2020-05-19 18:17:35.959180</time><SC_T1>27.18</SC_T1><CC_T1>25.51</CC_T1><DPG_T1>22.26</DPG_T1><pCO2>797.056</pCO2><pH2O>13.5961</pH2O><Sample_weight>0.4736328125</Sample_weight></TAData>
<?xml version="1.0" encoding="UTF-8" ?><TAData><time>2020-05-19 18:17:37.963594</time><SC_T1>27.18</SC_T1><CC_T1>25.75</CC_T1><DPG_T1>22.26</DPG_T1><pCO2>803.834</pCO2><pH2O>13.5069</pH2O><Sample_weight>0.478515625</Sample_weight></TAData>
<?xml version="1.0" encoding="UTF-8" ?><TAData><time>2020-05-19 18:17:40.031685</time><SC_T1>27.18</SC_T1><CC_T1>26.0</CC_T1><DPG_T1>22.26</DPG_T1><pCO2>810.563</pCO2><pH2O>13.4251</pH2O><Sample_weight>0.48095703125</Sample_weight></TAData>
<?xml version="1.0" encoding="UTF-8" ?><TAData><time>2020-05-19 18:17:42.064508</time><SC_T1>27.18</SC_T1><CC_T1>26.29</CC_T1><DPG_T1>22.26</DPG_T1><pCO2>819.004</pCO2><pH2O>13.286</pH2O><Sample_weight>0.48095703125</Sample_weight></TAData>
<?xml version="1.0" encoding="UTF-8" ?><TAData><time>2020-05-19 18:17:44.144525</time><SC_T1>27.18</SC_T1><CC_T1>26.6</CC_T1><DPG_T1>22.26</DPG_T1><pCO2>825.623</pCO2><pH2O>13.173</pH2O><Sample_weight>0.46875</Sample_weight></TAData>
<?xml version="1.0" encoding="UTF-8" ?><TAData><time>2020-05-19 18:17:46.231384</time><SC_T1>27.18</SC_T1><CC_T1>26.92</CC_T1><DPG_T1>22.26</DPG_T1><pCO2>836.804</pCO2><pH2O>13.0566</pH2O><Sample_weight>0.46875</Sample_weight></TAData>
<?xml version="1.0" encoding="UTF-8" ?><TAData><time>2020-05-19 18:17:48.273979</time><SC_T1>27.19</SC_T1><CC_T1>27.23</CC_T1><DPG_T1>22.27</DPG_T1><pCO2>839.488</pCO2><pH2O>12.9583</pH2O><Sample_weight>0.48828125</Sample_weight></TAData>
<?xml version="1.0" encoding="UTF-8" ?><TAData><time>2020-05-19 18:17:50.331895</time><SC_T1>27.19</SC_T1><CC_T1>27.57</CC_T1><DPG_T1>22.27</DPG_T1><pCO2>845.894</pCO2><pH2O>12.8659</pH2O><Sample_weight>0.4833984375</Sample_weight></TAData>
<?xml version="1.0" encoding="UTF-8" ?><TAData><time>2020-05-19 18:17:52.407651</time><SC_T1>27.19</SC_T1><CC_T1>27.9</CC_T1><DPG_T1>22.27</DPG_T1><pCO2>850.007</pCO2><pH2O>12.7973</pH2O><Sample_weight>0.46875</Sample_weight></TAData>
<?xml version="1.0" encoding="UTF-8" ?><TAData><time>2020-05-19 18:17:54.478442</time><SC_T1>27.19</SC_T1><CC_T1>28.23</CC_T1><DPG_T1>22.27</DPG_T1><pCO2>856.286</pCO2><pH2O>12.7062</pH2O><Sample_weight>0.478515625</Sample_weight></TAData>
<?xml version="1.0" encoding="UTF-8" ?><TAData><time>2020-05-19 18:17:56.557207</time><SC_T1>27.2</SC_T1><CC_T1>28.54</CC_T1><DPG_T1>22.27</DPG_T1><pCO2>859.136</pCO2><pH2O>12.6367</pH2O><Sample_weight>0.46875</Sample_weight></TAData>
<?xml version="1.0" encoding="UTF-8" ?><TAData><time>2020-05-19 18:17:58.565442</time><SC_T1>27.2</SC_T1><CC_T1>28.86</CC_T1><DPG_T1>22.27</DPG_T1><pCO2>861.204</pCO2><pH2O>12.58</pH2O><Sample_weight>0.4736328125</Sample_weight></TAData>
<?xml version="1.0" encoding="UTF-8" ?><TAData><time>2020-05-19 18:18:00.600258</time><SC_T1>27.2</SC_T1><CC_T1>29.18</CC_T1><DPG_T1>22.27</DPG_T1><pCO2>863.817</pCO2><pH2O>12.5424</pH2O><Sample_weight>0.4736328125</Sample_weight></TAData>
<?xml version="1.0" encoding="UTF-8" ?><TAData><time>2020-05-19 18:18:04.602131</time><SC_T1>27.2</SC_T1><CC_T1>29.45</CC_T1><DPG_T1>22.27</DPG_T1><pCO2>865.79</pCO2><pH2O>12.5063</pH2O><Sample_weight>0.47119140625</Sample_weight></TAData>
<?xml version="1.0" encoding="UTF-8" ?><TAData><time>2020-05-19 18:18:06.612330</time><SC_T1>27.2</SC_T1><CC_T1>29.71</CC_T1><DPG_T1>22.27</DPG_T1><pCO2>867.599</pCO2><pH2O>12.5011</pH2O><Sample_weight>0.48583984375</Sample_weight></TAData>
<?xml version="1.0" encoding="UTF-8" ?><TAData><time>2020-05-19 18:18:08.653116</time><SC_T1>27.2</SC_T1><CC_T1>29.96</CC_T1><DPG_T1>22.28</DPG_T1><pCO2>867.739</pCO2><pH2O>12.4817</pH2O><Sample_weight>0.48828125</Sample_weight></TAData>
<?xml version="1.0" encoding="UTF-8" ?><TAData><time>2020-05-19 18:18:10.667646</time><SC_T1>27.21</SC_T1><CC_T1>30.17</CC_T1><DPG_T1>22.28</DPG_T1><pCO2>867.984</pCO2><pH2O>12.4818</pH2O><Sample_weight>0.48583984375</Sample_weight></TAData>
<?xml version="1.0" encoding="UTF-8" ?><TAData><time>2020-05-19 18:18:12.669145</time><SC_T1>27.21</SC_T1><CC_T1>30.37</CC_T1><DPG_T1>22.28</DPG_T1><pCO2>866.0</pCO2><pH2O>12.4789</pH2O><Sample_weight>0.49560546875</Sample_weight></TAData>
<?xml version="1.0" encoding="UTF-8" ?><TAData><time>2020-05-19 18:18:14.671703</time><SC_T1>27.21</SC_T1><CC_T1>30.54</CC_T1><DPG_T1>22.28</DPG_T1><pCO2>866.402</pCO2><pH2O>12.4993</pH2O><Sample_weight>0.4833984375</Sample_weight></TAData>
<?xml version="1.0" encoding="UTF-8" ?><TAData><time>2020-05-19 18:18:16.675082</time><SC_T1>27.21</SC_T1><CC_T1>30.7</CC_T1><DPG_T1>22.28</DPG_T1><pCO2>864.408</pCO2><pH2O>12.5283</pH2O><Sample_weight>0.4931640625</Sample_weight></TAData>
<?xml version="1.0" encoding="UTF-8" ?><TAData><time>2020-05-19 18:18:18.677262</time><SC_T1>27.21</SC_T1><CC_T1>30.82</CC_T1><DPG_T1>22.28</DPG_T1><pCO2>861.84</pCO2><pH2O>12.5731</pH2O><Sample_weight>0.46875</Sample_weight></TAData>
<?xml version="1.0" encoding="UTF-8" ?><TAData><time>2020-05-19 18:18:20.679624</time><SC_T1>27.21</SC_T1><CC_T1>30.93</CC_T1><DPG_T1>22.28</DPG_T1><pCO2>860.515</pCO2><pH2O>12.5765</pH2O><Sample_weight>0.478515625</Sample_weight></TAData>
<?xml version="1.0" encoding="UTF-8" ?><TAData><time>2020-05-19 18:18:22.682998</time><SC_T1>27.22</SC_T1><CC_T1>31.02</CC_T1><DPG_T1>22.28</DPG_T1><pCO2>858.414</pCO2><pH2O>12.6141</pH2O><Sample_weight>0.47607421875</Sample_weight></TAData>
<?xml version="1.0" encoding="UTF-8" ?><TAData><time>2020-05-19 18:18:24.732157</time><SC_T1>27.22</SC_T1><CC_T1>31.08</CC_T1><DPG_T1>22.28</DPG_T1><pCO2>855.717</pCO2><pH2O>12.6482</pH2O><Sample_weight>0.4736328125</Sample_weight></TAData>
<?xml version="1.0" encoding="UTF-8" ?><TAData><time>2020-05-19 18:18:26.798795</time><SC_T1>27.22</SC_T1><CC_T1>31.15</CC_T1><DPG_T1>22.29</DPG_T1><pCO2>855.175</pCO2><pH2O>12.67</pH2O><Sample_weight>0.46875</Sample_weight></TAData>
<?xml version="1.0" encoding="UTF-8" ?><TAData><time>2020-05-19 18:18:28.867922</time><SC_T1>27.23</SC_T1><CC_T1>31.19</CC_T1><DPG_T1>22.29</DPG_T1><pCO2>852.287</pCO2><pH2O>12.7089</pH2O><Sample_weight>0.47607421875</Sample_weight></TAData>
<?xml version="1.0" encoding="UTF-8" ?><TAData><time>2020-05-19 18:18:30.942929</time><SC_T1>27.23</SC_T1><CC_T1>31.22</CC_T1><DPG_T1>22.29</DPG_T1><pCO2>849.607</pCO2><pH2O>12.7293</pH2O><Sample_weight>0.49072265625</Sample_weight></TAData>
<?xml version="1.0" encoding="UTF-8" ?><TAData><time>2020-05-19 18:18:33.012436</time><SC_T1>27.23</SC_T1><CC_T1>31.25</CC_T1><DPG_T1>22.29</DPG_T1><pCO2>847.917</pCO2><pH2O>12.7788</pH2O><Sample_weight>0.48095703125</Sample_weight></TAData>
<?xml version="1.0" encoding="UTF-8" ?><TAData><time>2020-05-19 18:18:35.077509</time><SC_T1>27.23</SC_T1><CC_T1>31.25</CC_T1><DPG_T1>22.3</DPG_T1><pCO2>844.534</pCO2><pH2O>12.7994</pH2O><Sample_weight>0.49072265625</Sample_weight></TAData>
<?xml version="1.0" encoding="UTF-8" ?><TAData><time>2020-05-19 18:18:37.144529</time><SC_T1>27.24</SC_T1><CC_T1>31.25</CC_T1><DPG_T1>22.3</DPG_T1><pCO2>845.211</pCO2><pH2O>12.8168</pH2O><Sample_weight>0.48828125</Sample_weight></TAData>
<?xml version="1.0" encoding="UTF-8" ?><TAData><time>2020-05-19 18:18:39.212486</time><SC_T1>27.24</SC_T1><CC_T1>31.23</CC_T1><DPG_T1>22.3</DPG_T1><pCO2>843.371</pCO2><pH2O>12.8368</pH2O><Sample_weight>0.4833984375</Sample_weight></TAData>
<?xml version="1.0" encoding="UTF-8" ?><TAData><time>2020-05-19 18:18:41.279562</time><SC_T1>27.25</SC_T1><CC_T1>31.21</CC_T1><DPG_T1>22.3</DPG_T1><pCO2>841.187</pCO2><pH2O>12.8421</pH2O><Sample_weight>0.47119140625</Sample_weight></TAData>
<?xml version="1.0" encoding="UTF-8" ?><TAData><time>2020-05-19 18:18:43.349132</time><SC_T1>27.25</SC_T1><CC_T1>31.18</CC_T1><DPG_T1>22.3</DPG_T1><pCO2>842.181</pCO2><pH2O>12.8556</pH2O><Sample_weight>0.48095703125</Sample_weight></TAData>
<?xml version="1.0" encoding="UTF-8" ?><TAData><time>2020-05-19 18:18:45.411015</time><SC_T1>27.25</SC_T1><CC_T1>31.15</CC_T1><DPG_T1>22.3</DPG_T1><pCO2>839.474</pCO2><pH2O>12.8701</pH2O><Sample_weight>0.48583984375</Sample_weight></TAData>
<?xml version="1.0" encoding="UTF-8" ?><TAData><time>2020-05-19 18:18:47.434559</time><SC_T1>27.25</SC_T1><CC_T1>31.12</CC_T1><DPG_T1>22.3</DPG_T1><pCO2>838.233</pCO2><pH2O>12.8847</pH2O><Sample_weight>0.48095703125</Sample_weight></TAData>
<?xml version="1.0" encoding="UTF-8" ?><TAData><time>2020-05-19 18:18:49.468448</time><SC_T1>27.26</SC_T1><CC_T1>31.07</CC_T1><DPG_T1>22.3</DPG_T1><pCO2>835.812</pCO2><pH2O>12.8794</pH2O><Sample_weight>0.49072265625</Sample_weight></TAData>
<?xml version="1.0" encoding="UTF-8" ?><TAData><time>2020-05-19 18:18:51.486618</time><SC_T1>27.26</SC_T1><CC_T1>31.02</CC_T1><DPG_T1>22.3</DPG_T1><pCO2>835.362</pCO2><pH2O>12.8989</pH2O><Sample_weight>0.4736328125</Sample_weight></TAData>
<?xml version="1.0" encoding="UTF-8" ?><TAData><time>2020-05-19 18:18:53.503526</time><SC_T1>27.26</SC_T1><CC_T1>30.97</CC_T1><DPG_T1>22.3</DPG_T1><pCO2>832.888</pCO2><pH2O>12.9211</pH2O><Sample_weight>0.47607421875</Sample_weight></TAData>
<?xml version="1.0" encoding="UTF-8" ?><TAData><time>2020-05-19 18:18:55.515963</time><SC_T1>27.27</SC_T1><CC_T1>30.92</CC_T1><DPG_T1>22.3</DPG_T1><pCO2>831.668</pCO2><pH2O>12.9386</pH2O><Sample_weight>0.47119140625</Sample_weight></TAData>
<?xml version="1.0" encoding="UTF-8" ?><TAData><time>2020-05-19 18:18:57.521505</time><SC_T1>27.27</SC_T1><CC_T1>30.86</CC_T1><DPG_T1>22.3</DPG_T1><pCO2>832.203</pCO2><pH2O>12.9295</pH2O><Sample_weight>0.4833984375</Sample_weight></TAData>
<?xml version="1.0" encoding="UTF-8" ?><TAData><time>2020-05-19 18:18:59.533920</time><SC_T1>27.27</SC_T1><CC_T1>30.81</CC_T1><DPG_T1>22.3</DPG_T1><pCO2>828.873</pCO2><pH2O>12.9327</pH2O><Sample_weight>0.4833984375</Sample_weight></TAData>
<?xml version="1.0" encoding="UTF-8" ?><TAData><time>2020-05-19 18:19:01.535441</time><SC_T1>27.27</SC_T1><CC_T1>30.76</CC_T1><DPG_T1>22.3</DPG_T1><pCO2>829.063</pCO2><pH2O>12.9204</pH2O><Sample_weight>0.48828125</Sample_weight></TAData>
<?xml version="1.0" encoding="UTF-8" ?><TAData><time>2020-05-19 18:19:03.584796</time><SC_T1>27.28</SC_T1><CC_T1>30.71</CC_T1><DPG_T1>22.3</DPG_T1><pCO2>826.752</pCO2><pH2O>12.944</pH2O><Sample_weight>0.48828125</Sample_weight></TAData>
<?xml version="1.0" encoding="UTF-8" ?><TAData><time>2020-05-19 18:19:05.587325</time><SC_T1>27.28</SC_T1><CC_T1>30.66</CC_T1><DPG_T1>22.3</DPG_T1><pCO2>827.725</pCO2><pH2O>12.9496</pH2O><Sample_weight>0.4736328125</Sample_weight></TAData>
<?xml version="1.0" encoding="UTF-8" ?><TAData><time>2020-05-19 18:19:07.588892</time><SC_T1>27.28</SC_T1><CC_T1>30.61</CC_T1><DPG_T1>22.3</DPG_T1><pCO2>826.204</pCO2><pH2O>12.9509</pH2O><Sample_weight>0.4736328125</Sample_weight></TAData>
<?xml version="1.0" encoding="UTF-8" ?><TAData><time>2020-05-19 18:19:09.631511</time><SC_T1>27.29</SC_T1><CC_T1>30.56</CC_T1><DPG_T1>22.3</DPG_T1><pCO2>821.769</pCO2><pH2O>12.943</pH2O><Sample_weight>0.47607421875</Sample_weight></TAData>
<?xml version="1.0" encoding="UTF-8" ?><TAData><time>2020-05-19 18:19:13.644767</time><SC_T1>27.29</SC_T1><CC_T1>30.51</CC_T1><DPG_T1>22.3</DPG_T1><pCO2>822.164</pCO2><pH2O>12.9347</pH2O><Sample_weight>0.47607421875</Sample_weight></TAData>
<?xml version="1.0" encoding="UTF-8" ?><TAData><time>2020-05-19 18:19:15.648190</time><SC_T1>27.29</SC_T1><CC_T1>30.47</CC_T1><DPG_T1>22.31</DPG_T1><pCO2>818.787</pCO2><pH2O>12.9381</pH2O><Sample_weight>0.478515625</Sample_weight></TAData>
<?xml version="1.0" encoding="UTF-8" ?><TAData><time>2020-05-19 18:19:17.650298</time><SC_T1>27.3</SC_T1><CC_T1>30.43</CC_T1><DPG_T1>22.31</DPG_T1><pCO2>820.358</pCO2><pH2O>12.9412</pH2O><Sample_weight>0.48828125</Sample_weight></TAData>
<?xml version="1.0" encoding="UTF-8" ?><TAData><time>2020-05-19 18:19:19.652122</time><SC_T1>27.3</SC_T1><CC_T1>30.38</CC_T1><DPG_T1>22.31</DPG_T1><pCO2>821.747</pCO2><pH2O>12.9416</pH2O><Sample_weight>0.48095703125</Sample_weight></TAData>
<?xml version="1.0" encoding="UTF-8" ?><TAData><time>2020-05-19 18:19:21.655462</time><SC_T1>27.3</SC_T1><CC_T1>30.35</CC_T1><DPG_T1>22.31</DPG_T1><pCO2>818.435</pCO2><pH2O>12.939</pH2O><Sample_weight>0.478515625</Sample_weight></TAData>
<?xml version="1.0" encoding="UTF-8" ?><TAData><time>2020-05-19 18:19:23.665896</time><SC_T1>27.3</SC_T1><CC_T1>30.31</CC_T1><DPG_T1>22.31</DPG_T1><pCO2>820.201</pCO2><pH2O>12.9358</pH2O><Sample_weight>0.4833984375</Sample_weight></TAData>
<?xml version="1.0" encoding="UTF-8" ?><TAData><time>2020-05-19 18:19:25.686965</time><SC_T1>27.3</SC_T1><CC_T1>30.27</CC_T1><DPG_T1>22.31</DPG_T1><pCO2>812.999</pCO2><pH2O>12.944</pH2O><Sample_weight>0.48828125</Sample_weight></TAData>
<?xml version="1.0" encoding="UTF-8" ?><TAData><time>2020-05-19 18:19:27.705386</time><SC_T1>27.31</SC_T1><CC_T1>30.24</CC_T1><DPG_T1>22.31</DPG_T1><pCO2>816.574</pCO2><pH2O>12.9479</pH2O><Sample_weight>0.48095703125</Sample_weight></TAData>
<?xml version="1.0" encoding="UTF-8" ?><TAData><time>2020-05-19 18:19:29.736998</time><SC_T1>27.31</SC_T1><CC_T1>30.21</CC_T1><DPG_T1>22.31</DPG_T1><pCO2>814.569</pCO2><pH2O>12.9506</pH2O><Sample_weight>0.478515625</Sample_weight></TAData>
<?xml version="1.0" encoding="UTF-8" ?><TAData><time>2020-05-19 18:19:31.751525</time><SC_T1>27.31</SC_T1><CC_T1>30.17</CC_T1><DPG_T1>22.31</DPG_T1><pCO2>817.885</pCO2><pH2O>12.9486</pH2O><Sample_weight>0.478515625</Sample_weight></TAData>
<?xml version="1.0" encoding="UTF-8" ?><TAData><time>2020-05-19 18:19:33.753071</time><SC_T1>27.31</SC_T1><CC_T1>30.15</CC_T1><DPG_T1>22.32</DPG_T1><pCO2>815.074</pCO2><pH2O>12.9506</pH2O><Sample_weight>0.47119140625</Sample_weight></TAData>
<?xml version="1.0" encoding="UTF-8" ?><TAData><time>2020-05-19 18:19:35.756353</time><SC_T1>27.31</SC_T1><CC_T1>30.11</CC_T1><DPG_T1>22.31</DPG_T1><pCO2>816.371</pCO2><pH2O>12.9536</pH2O><Sample_weight>0.4736328125</Sample_weight></TAData>
<?xml version="1.0" encoding="UTF-8" ?><TAData><time>2020-05-19 18:19:37.769057</time><SC_T1>27.31</SC_T1><CC_T1>30.09</CC_T1><DPG_T1>22.32</DPG_T1><pCO2>815.021</pCO2><pH2O>12.954</pH2O><Sample_weight>0.48828125</Sample_weight></TAData>
<?xml version="1.0" encoding="UTF-8" ?><TAData><time>2020-05-19 18:19:39.771871</time><SC_T1>27.31</SC_T1><CC_T1>30.06</CC_T1><DPG_T1>22.32</DPG_T1><pCO2>815.284</pCO2><pH2O>12.9521</pH2O><Sample_weight>0.48095703125</Sample_weight></TAData>
<?xml version="1.0" encoding="UTF-8" ?><TAData><time>2020-05-19 18:19:41.784594</time><SC_T1>27.32</SC_T1><CC_T1>30.05</CC_T1><DPG_T1>22.32</DPG_T1><pCO2>814.291</pCO2><pH2O>12.9372</pH2O><Sample_weight>0.49560546875</Sample_weight></TAData>
<?xml version="1.0" encoding="UTF-8" ?><TAData><time>2020-05-19 18:19:43.786671</time><SC_T1>27.32</SC_T1><CC_T1>30.02</CC_T1><DPG_T1>22.32</DPG_T1><pCO2>814.456</pCO2><pH2O>12.9563</pH2O><Sample_weight>0.4833984375</Sample_weight></TAData>
<?xml version="1.0" encoding="UTF-8" ?><TAData><time>2020-05-19 18:19:45.805212</time><SC_T1>27.32</SC_T1><CC_T1>30.0</CC_T1><DPG_T1>22.32</DPG_T1><pCO2>815.396</pCO2><pH2O>12.9611</pH2O><Sample_weight>0.48828125</Sample_weight></TAData>
<?xml version="1.0" encoding="UTF-8" ?><TAData><time>2020-05-19 18:19:47.807061</time><SC_T1>27.32</SC_T1><CC_T1>29.98</CC_T1><DPG_T1>22.32</DPG_T1><pCO2>814.515</pCO2><pH2O>12.9414</pH2O><Sample_weight>0.49560546875</Sample_weight></TAData>
<?xml version="1.0" encoding="UTF-8" ?><TAData><time>2020-05-19 18:19:49.809980</time><SC_T1>27.32</SC_T1><CC_T1>29.96</CC_T1><DPG_T1>22.32</DPG_T1><pCO2>813.029</pCO2><pH2O>12.9404</pH2O><Sample_weight>0.48828125</Sample_weight></TAData>
<?xml version="1.0" encoding="UTF-8" ?><TAData><time>2020-05-19 18:19:51.813573</time><SC_T1>27.32</SC_T1><CC_T1>29.95</CC_T1><DPG_T1>22.32</DPG_T1><pCO2>811.928</pCO2><pH2O>12.9371</pH2O><Sample_weight>0.48583984375</Sample_weight></TAData>
<?xml version="1.0" encoding="UTF-8" ?><TAData><time>2020-05-19 18:19:53.817341</time><SC_T1>27.32</SC_T1><CC_T1>29.93</CC_T1><DPG_T1>22.32</DPG_T1><pCO2>812.695</pCO2><pH2O>12.9529</pH2O><Sample_weight>0.48828125</Sample_weight></TAData>
<?xml version="1.0" encoding="UTF-8" ?><TAData><time>2020-05-19 18:19:55.819862</time><SC_T1>27.32</SC_T1><CC_T1>29.92</CC_T1><DPG_T1>22.32</DPG_T1><pCO2>813.145</pCO2><pH2O>12.9356</pH2O><Sample_weight>0.48095703125</Sample_weight></TAData>
<?xml version="1.0" encoding="UTF-8" ?><TAData><time>2020-05-19 18:19:57.825668</time><SC_T1>27.32</SC_T1><CC_T1>29.91</CC_T1><DPG_T1>22.32</DPG_T1><pCO2>811.472</pCO2><pH2O>12.9406</pH2O><Sample_weight>0.478515625</Sample_weight></TAData>
<?xml version="1.0" encoding="UTF-8" ?><TAData><time>2020-05-19 18:19:59.896660</time><SC_T1>27.33</SC_T1><CC_T1>29.9</CC_T1><DPG_T1>22.32</DPG_T1><pCO2>810.781</pCO2><pH2O>12.9442</pH2O><Sample_weight>0.48828125</Sample_weight></TAData>
<?xml version="1.0" encoding="UTF-8" ?><TAData><time>2020-05-19 18:20:03.946642</time><SC_T1>27.33</SC_T1><CC_T1>29.89</CC_T1><DPG_T1>22.32</DPG_T1><pCO2>811.673</pCO2><pH2O>12.9618</pH2O><Sample_weight>0.4638671875</Sample_weight></TAData>
<?xml version="1.0" encoding="UTF-8" ?><TAData><time>2020-05-19 18:20:05.958807</time><SC_T1>27.33</SC_T1><CC_T1>29.88</CC_T1><DPG_T1>22.32</DPG_T1><pCO2>811.915</pCO2><pH2O>12.965</pH2O><Sample_weight>0.49072265625</Sample_weight></TAData>
<?xml version="1.0" encoding="UTF-8" ?><TAData><time>2020-05-19 18:20:07.985647</time><SC_T1>27.33</SC_T1><CC_T1>29.88</CC_T1><DPG_T1>22.32</DPG_T1><pCO2>811.882</pCO2><pH2O>12.9377</pH2O><Sample_weight>0.48095703125</Sample_weight></TAData>
<?xml version="1.0" encoding="UTF-8" ?><TAData><time>2020-05-19 18:20:09.998647</time><SC_T1>27.33</SC_T1><CC_T1>29.87</CC_T1><DPG_T1>22.32</DPG_T1><pCO2>810.4</pCO2><pH2O>12.9461</pH2O><Sample_weight>0.4736328125</Sample_weight></TAData>
<?xml version="1.0" encoding="UTF-8" ?><TAData><time>2020-05-19 18:20:12.000145</time><SC_T1>27.33</SC_T1><CC_T1>29.87</CC_T1><DPG_T1>22.32</DPG_T1><pCO2>810.39</pCO2><pH2O>12.9398</pH2O><Sample_weight>0.48583984375</Sample_weight></TAData>
<?xml version="1.0" encoding="UTF-8" ?><TAData><time>2020-05-19 18:20:14.014760</time><SC_T1>27.33</SC_T1><CC_T1>29.86</CC_T1><DPG_T1>22.32</DPG_T1><pCO2>813.438</pCO2><pH2O>12.9549</pH2O><Sample_weight>0.47607421875</Sample_weight></TAData>
<?xml version="1.0" encoding="UTF-8" ?><TAData><time>2020-05-19 18:20:16.016210</time><SC_T1>27.33</SC_T1><CC_T1>29.86</CC_T1><DPG_T1>22.32</DPG_T1><pCO2>811.534</pCO2><pH2O>12.9516</pH2O><Sample_weight>0.478515625</Sample_weight></TAData>
<?xml version="1.0" encoding="UTF-8" ?><TAData><time>2020-05-19 18:20:18.022114</time><SC_T1>27.33</SC_T1><CC_T1>29.85</CC_T1><DPG_T1>22.32</DPG_T1><pCO2>813.567</pCO2><pH2O>12.947</pH2O><Sample_weight>0.47607421875</Sample_weight></TAData>
<?xml version="1.0" encoding="UTF-8" ?><TAData><time>2020-05-19 18:20:20.038471</time><SC_T1>27.33</SC_T1><CC_T1>29.85</CC_T1><DPG_T1>22.32</DPG_T1><pCO2>812.162</pCO2><pH2O>12.9481</pH2O><Sample_weight>0.478515625</Sample_weight></TAData>
<?xml version="1.0" encoding="UTF-8" ?><TAData><time>2020-05-19 18:20:22.040026</time><SC_T1>27.33</SC_T1><CC_T1>29.85</CC_T1><DPG_T1>22.32</DPG_T1><pCO2>810.686</pCO2><pH2O>12.9363</pH2O><Sample_weight>0.4736328125</Sample_weight></TAData>
<?xml version="1.0" encoding="UTF-8" ?><TAData><time>2020-05-19 18:20:24.087760</time><SC_T1>27.33</SC_T1><CC_T1>29.85</CC_T1><DPG_T1>22.32</DPG_T1><pCO2>813.758</pCO2><pH2O>12.9416</pH2O><Sample_weight>0.48583984375</Sample_weight></TAData>
<?xml version="1.0" encoding="UTF-8" ?><TAData><time>2020-05-19 18:20:26.106137</time><SC_T1>27.33</SC_T1><CC_T1>29.86</CC_T1><DPG_T1>22.32</DPG_T1><pCO2>810.128</pCO2><pH2O>12.9552</pH2O><Sample_weight>0.478515625</Sample_weight></TAData>
<?xml version="1.0" encoding="UTF-8" ?><TAData><time>2020-05-19 18:20:28.107681</time><SC_T1>27.33</SC_T1><CC_T1>29.86</CC_T1><DPG_T1>22.32</DPG_T1><pCO2>811.375</pCO2><pH2O>12.9429</pH2O><Sample_weight>0.49072265625</Sample_weight></TAData>
<?xml version="1.0" encoding="UTF-8" ?><TAData><time>2020-05-19 18:20:30.109275</time><SC_T1>27.33</SC_T1><CC_T1>29.87</CC_T1><DPG_T1>22.32</DPG_T1><pCO2>810.119</pCO2><pH2O>12.9446</pH2O><Sample_weight>0.48583984375</Sample_weight></TAData>
<?xml version="1.0" encoding="UTF-8" ?><TAData><time>2020-05-19 18:20:32.112219</time><SC_T1>27.33</SC_T1><CC_T1>29.87</CC_T1><DPG_T1>22.32</DPG_T1><pCO2>812.528</pCO2><pH2O>12.9371</pH2O><Sample_weight>0.48095703125</Sample_weight></TAData>
<?xml version="1.0" encoding="UTF-8" ?><TAData><time>2020-05-19 18:20:34.115527</time><SC_T1>27.33</SC_T1><CC_T1>29.88</CC_T1><DPG_T1>22.32</DPG_T1><pCO2>812.657</pCO2><pH2O>12.953</pH2O><Sample_weight>0.4931640625</Sample_weight></TAData>
<?xml version="1.0" encoding="UTF-8" ?><TAData><time>2020-05-19 18:20:36.118311</time><SC_T1>27.33</SC_T1><CC_T1>29.88</CC_T1><DPG_T1>22.32</DPG_T1><pCO2>812.368</pCO2><pH2O>12.9382</pH2O><Sample_weight>0.48583984375</Sample_weight></TAData>
<?xml version="1.0" encoding="UTF-8" ?><TAData><time>2020-05-19 18:20:38.134399</time><SC_T1>27.33</SC_T1><CC_T1>29.89</CC_T1><DPG_T1>22.32</DPG_T1><pCO2>811.436</pCO2><pH2O>12.9538</pH2O><Sample_weight>0.47607421875</Sample_weight></TAData>
<?xml version="1.0" encoding="UTF-8" ?><TAData><time>2020-05-19 18:20:40.136466</time><SC_T1>27.33</SC_T1><CC_T1>29.89</CC_T1><DPG_T1>22.32</DPG_T1><pCO2>812.051</pCO2><pH2O>12.938</pH2O><Sample_weight>0.47607421875</Sample_weight></TAData>
<?xml version="1.0" encoding="UTF-8" ?><TAData><time>2020-05-19 18:20:42.151456</time><SC_T1>27.33</SC_T1><CC_T1>29.89</CC_T1><DPG_T1>22.32</DPG_T1><pCO2>810.969</pCO2><pH2O>12.9362</pH2O><Sample_weight>0.47607421875</Sample_weight></TAData>
<?xml version="1.0" encoding="UTF-8" ?><TAData><time>2020-05-19 18:20:44.172388</time><SC_T1>27.33</SC_T1><CC_T1>29.9</CC_T1><DPG_T1>22.32</DPG_T1><pCO2>812.285</pCO2><pH2O>12.9604</pH2O><Sample_weight>0.4931640625</Sample_weight></TAData>
<?xml version="1.0" encoding="UTF-8" ?><TAData><time>2020-05-19 18:20:46.195045</time><SC_T1>27.34</SC_T1><CC_T1>29.9</CC_T1><DPG_T1>22.32</DPG_T1><pCO2>810.523</pCO2><pH2O>12.9672</pH2O><Sample_weight>0.48095703125</Sample_weight></TAData>
<?xml version="1.0" encoding="UTF-8" ?><TAData><time>2020-05-19 18:20:48.201113</time><SC_T1>27.33</SC_T1><CC_T1>29.91</CC_T1><DPG_T1>22.32</DPG_T1><pCO2>811.144</pCO2><pH2O>12.9507</pH2O><Sample_weight>0.46875</Sample_weight></TAData>
<?xml version="1.0" encoding="UTF-8" ?><TAData><time>2020-05-19 18:20:50.226040</time><SC_T1>27.34</SC_T1><CC_T1>29.91</CC_T1><DPG_T1>22.32</DPG_T1><pCO2>808.988</pCO2><pH2O>12.9719</pH2O><Sample_weight>0.4931640625</Sample_weight></TAData>
<?xml version="1.0" encoding="UTF-8" ?><TAData><time>2020-05-19 18:20:52.227619</time><SC_T1>27.34</SC_T1><CC_T1>29.91</CC_T1><DPG_T1>22.32</DPG_T1><pCO2>812.271</pCO2><pH2O>12.9576</pH2O><Sample_weight>0.4833984375</Sample_weight></TAData>
<?xml version="1.0" encoding="UTF-8" ?><TAData><time>2020-05-19 18:20:56.279259</time><SC_T1>27.33</SC_T1><CC_T1>29.91</CC_T1><DPG_T1>22.32</DPG_T1><pCO2>808.837</pCO2><pH2O>12.9587</pH2O><Sample_weight>0.49560546875</Sample_weight></TAData>
<?xml version="1.0" encoding="UTF-8" ?><TAData><time>2020-05-19 18:20:58.292561</time><SC_T1>27.34</SC_T1><CC_T1>29.91</CC_T1><DPG_T1>22.32</DPG_T1><pCO2>810.62</pCO2><pH2O>12.976</pH2O><Sample_weight>0.48828125</Sample_weight></TAData>
<?xml version="1.0" encoding="UTF-8" ?><TAData><time>2020-05-19 18:21:00.294346</time><SC_T1>27.34</SC_T1><CC_T1>29.91</CC_T1><DPG_T1>22.32</DPG_T1><pCO2>810.962</pCO2><pH2O>12.9742</pH2O><Sample_weight>0.48828125</Sample_weight></TAData>
<?xml version="1.0" encoding="UTF-8" ?><TAData><time>2020-05-19 18:21:02.328234</time><SC_T1>27.34</SC_T1><CC_T1>29.91</CC_T1><DPG_T1>22.32</DPG_T1><pCO2>809.24</pCO2><pH2O>12.971</pH2O><Sample_weight>0.4833984375</Sample_weight></TAData>
<?xml version="1.0" encoding="UTF-8" ?><TAData><time>2020-05-19 18:21:04.329913</time><SC_T1>27.34</SC_T1><CC_T1>29.91</CC_T1><DPG_T1>22.32</DPG_T1><pCO2>811.194</pCO2><pH2O>12.9679</pH2O><Sample_weight>0.47607421875</Sample_weight></TAData>
<?xml version="1.0" encoding="UTF-8" ?><TAData><time>2020-05-19 18:21:06.332714</time><SC_T1>27.34</SC_T1><CC_T1>29.91</CC_T1><DPG_T1>22.32</DPG_T1><pCO2>809.751</pCO2><pH2O>12.9763</pH2O><Sample_weight>0.46875</Sample_weight></TAData>
<?xml version="1.0" encoding="UTF-8" ?><TAData><time>2020-05-19 18:21:08.334302</time><SC_T1>27.34</SC_T1><CC_T1>29.91</CC_T1><DPG_T1>22.32</DPG_T1><pCO2>809.425</pCO2><pH2O>12.9823</pH2O><Sample_weight>0.47119140625</Sample_weight></TAData>
<?xml version="1.0" encoding="UTF-8" ?><TAData><time>2020-05-19 18:21:10.335854</time><SC_T1>27.34</SC_T1><CC_T1>29.9</CC_T1><DPG_T1>22.32</DPG_T1><pCO2>810.527</pCO2><pH2O>12.9735</pH2O><Sample_weight>0.478515625</Sample_weight></TAData>
<?xml version="1.0" encoding="UTF-8" ?><TAData><time>2020-05-19 18:21:12.339221</time><SC_T1>27.34</SC_T1><CC_T1>29.9</CC_T1><DPG_T1>22.32</DPG_T1><pCO2>810.899</pCO2><pH2O>12.9846</pH2O><Sample_weight>0.47119140625</Sample_weight></TAData>
<?xml version="1.0" encoding="UTF-8" ?><TAData><time>2020-05-19 18:21:14.368431</time><SC_T1>27.34</SC_T1><CC_T1>29.9</CC_T1><DPG_T1>22.32</DPG_T1><pCO2>810.965</pCO2><pH2O>12.9708</pH2O><Sample_weight>0.478515625</Sample_weight></TAData>
<?xml version="1.0" encoding="UTF-8" ?><TAData><time>2020-05-19 18:21:16.398687</time><SC_T1>27.34</SC_T1><CC_T1>29.89</CC_T1><DPG_T1>22.32</DPG_T1><pCO2>808.546</pCO2><pH2O>12.9919</pH2O><Sample_weight>0.4833984375</Sample_weight></TAData>
<?xml version="1.0" encoding="UTF-8" ?><TAData><time>2020-05-19 18:21:18.418825</time><SC_T1>27.34</SC_T1><CC_T1>29.88</CC_T1><DPG_T1>22.32</DPG_T1><pCO2>809.783</pCO2><pH2O>13.0032</pH2O><Sample_weight>0.49072265625</Sample_weight></TAData>
<?xml version="1.0" encoding="UTF-8" ?><TAData><time>2020-05-19 18:21:20.440203</time><SC_T1>27.34</SC_T1><CC_T1>29.88</CC_T1><DPG_T1>22.32</DPG_T1><pCO2>807.709</pCO2><pH2O>12.9812</pH2O><Sample_weight>0.4833984375</Sample_weight></TAData>
<?xml version="1.0" encoding="UTF-8" ?><TAData><time>2020-05-19 18:21:22.478806</time><SC_T1>27.34</SC_T1><CC_T1>29.87</CC_T1><DPG_T1>22.32</DPG_T1><pCO2>811.804</pCO2><pH2O>12.9844</pH2O><Sample_weight>0.48828125</Sample_weight></TAData>
<?xml version="1.0" encoding="UTF-8" ?><TAData><time>2020-05-19 18:21:24.487300</time><SC_T1>27.35</SC_T1><CC_T1>29.87</CC_T1><DPG_T1>22.32</DPG_T1><pCO2>808.727</pCO2><pH2O>12.9901</pH2O><Sample_weight>0.48095703125</Sample_weight></TAData>
<?xml version="1.0" encoding="UTF-8" ?><TAData><time>2020-05-19 18:21:26.488717</time><SC_T1>27.35</SC_T1><CC_T1>29.87</CC_T1><DPG_T1>22.32</DPG_T1><pCO2>807.688</pCO2><pH2O>12.9863</pH2O><Sample_weight>0.4833984375</Sample_weight></TAData>
<?xml version="1.0" encoding="UTF-8" ?><TAData><time>2020-05-19 18:21:28.532490</time><SC_T1>27.35</SC_T1><CC_T1>29.87</CC_T1><DPG_T1>22.32</DPG_T1><pCO2>807.005</pCO2><pH2O>12.976</pH2O><Sample_weight>0.48583984375</Sample_weight></TAData>
<?xml version="1.0" encoding="UTF-8" ?><TAData><time>2020-05-19 18:21:30.544367</time><SC_T1>27.35</SC_T1><CC_T1>29.86</CC_T1><DPG_T1>22.32</DPG_T1><pCO2>807.423</pCO2><pH2O>13.007</pH2O><Sample_weight>0.47119140625</Sample_weight></TAData>
<?xml version="1.0" encoding="UTF-8" ?><TAData><time>2020-05-19 18:21:32.546216</time><SC_T1>27.35</SC_T1><CC_T1>29.86</CC_T1><DPG_T1>22.32</DPG_T1><pCO2>808.565</pCO2><pH2O>12.9848</pH2O><Sample_weight>0.47607421875</Sample_weight></TAData>
<?xml version="1.0" encoding="UTF-8" ?><TAData><time>2020-05-19 18:21:34.549356</time><SC_T1>27.35</SC_T1><CC_T1>29.86</CC_T1><DPG_T1>22.32</DPG_T1><pCO2>808.734</pCO2><pH2O>12.9984</pH2O><Sample_weight>0.46875</Sample_weight></TAData>
<?xml version="1.0" encoding="UTF-8" ?><TAData><time>2020-05-19 18:21:36.591402</time><SC_T1>27.35</SC_T1><CC_T1>29.86</CC_T1><DPG_T1>22.32</DPG_T1><pCO2>807.17</pCO2><pH2O>12.9848</pH2O><Sample_weight>0.48095703125</Sample_weight></TAData>
<?xml version="1.0" encoding="UTF-8" ?><TAData><time>2020-05-19 18:21:38.609089</time><SC_T1>27.35</SC_T1><CC_T1>29.86</CC_T1><DPG_T1>22.32</DPG_T1><pCO2>807.779</pCO2><pH2O>13.0196</pH2O><Sample_weight>0.4833984375</Sample_weight></TAData>
<?xml version="1.0" encoding="UTF-8" ?><TAData><time>2020-05-19 18:21:40.619207</time><SC_T1>27.35</SC_T1><CC_T1>29.86</CC_T1><DPG_T1>22.32</DPG_T1><pCO2>805.856</pCO2><pH2O>13.0028</pH2O><Sample_weight>0.49072265625</Sample_weight></TAData>
<?xml version="1.0" encoding="UTF-8" ?><TAData><time>2020-05-19 18:21:42.646071</time><SC_T1>27.35</SC_T1><CC_T1>29.86</CC_T1><DPG_T1>22.32</DPG_T1><pCO2>806.782</pCO2><pH2O>13.0066</pH2O><Sample_weight>0.47607421875</Sample_weight></TAData>
<?xml version="1.0" encoding="UTF-8" ?><TAData><time>2020-05-19 18:21:44.647781</time><SC_T1>27.35</SC_T1><CC_T1>29.86</CC_T1><DPG_T1>22.32</DPG_T1><pCO2>808.884</pCO2><pH2O>13.0145</pH2O><Sample_weight>0.48095703125</Sample_weight></TAData>
<?xml version="1.0" encoding="UTF-8" ?><TAData><time>2020-05-19 18:21:46.649486</time><SC_T1>27.35</SC_T1><CC_T1>29.85</CC_T1><DPG_T1>22.32</DPG_T1><pCO2>807.006</pCO2><pH2O>13.0137</pH2O><Sample_weight>0.48583984375</Sample_weight></TAData>
<?xml version="1.0" encoding="UTF-8" ?><TAData><time>2020-05-19 18:21:48.651106</time><SC_T1>27.35</SC_T1><CC_T1>29.85</CC_T1><DPG_T1>22.32</DPG_T1><pCO2>808.667</pCO2><pH2O>13.0251</pH2O><Sample_weight>0.478515625</Sample_weight></TAData>
<?xml version="1.0" encoding="UTF-8" ?><TAData><time>2020-05-19 18:21:52.653163</time><SC_T1>27.35</SC_T1><CC_T1>29.85</CC_T1><DPG_T1>22.32</DPG_T1><pCO2>807.006</pCO2><pH2O>13.0096</pH2O><Sample_weight>0.478515625</Sample_weight></TAData>
